{
  "_id": "4dCFhbFdRyzMpLzM",
  "name": "Wildhunt",
  "type": "feat",
  "img": "icons/creatures/abilities/wolf-heads-swirl-purple.webp",
  "effects": [],
  "folder": null,
  "sort": 0,
  "flags": {
    "betterRolls5e": {
      "quickDesc": {
        "value": true,
        "altValue": true
      },
      "quickProperties": {
        "value": true,
        "altValue": true
      },
      "quickOther": {
        "value": true,
        "altValue": true
      },
      "quickFlavor": {
        "value": true,
        "altValue": true
      }
    },
    "core": {
      "sourceId": "Item.BL6zdzu3WaMiudnV"
    },
    "mre-dnd5e": {
      "formulaGroups": [
        {
          "label": "Primary",
          "formulaSet": []
        }
      ]
    },
    "magicitems": {
      "enabled": false,
      "equipped": false,
      "attuned": false,
      "charges": "0",
      "chargeType": "c1",
      "destroy": false,
      "destroyFlavorText": "reaches 0 charges: it crumbles into ashes and is destroyed.",
      "rechargeable": false,
      "recharge": "0",
      "rechargeType": "t1",
      "rechargeUnit": "r1",
      "sorting": "l"
    }
  },
  "_stats": {
    "coreVersion": "12.331",
    "systemId": null,
    "systemVersion": null,
    "createdTime": null,
    "modifiedTime": null,
    "lastModifiedBy": null,
    "compendiumSource": null,
    "duplicateSource": null
  },
  "ownership": {
    "default": 0,
    "LCw1mxC8S2Al3dWA": 3
  },
  "system": {
    "description": {
      "value": "<p>Les Wildhunt shifters sont perspicaces et intuitifs. Certains sont constamment en alerte, toujours vigilants face aux menaces potentielles. D'autres se concentrent sur leur intuition, cherchant en eux-mêmes. Les Wildhunt shifters sont d'excellents chasseurs, et ils ont tendance à devenir les leaders spirituels des communautés de shifters.</p>\n<p><strong>Augmentation des caractéristiques.</strong> Votre score de Sagesse augmente de 2.</p>\n<p><strong>Pisteur naturel.</strong> Vous êtes compétent dans la compétence de survie.</p>\n<p><strong>Marquer l'odeur.</strong> En tant qu'action bonus, vous pouvez marquer une créature que vous pouvez voir à moins de 3.048 mètres de vous. Jusqu'à la fin de votre prochain long repos, votre bonus de compétence est doublé pour toute vérification de compétence que vous effectuez pour trouver la créature marquée, et vous connaissez toujours l'emplacement de cette créature si elle est à moins de 18.288 mètres de vous. Vous ne pouvez pas utiliser ce trait à nouveau jusqu'à ce que vous terminiez un court ou long repos.</p>\n<p><strong>Caractéristique de changement.</strong> Lorsqu'il est transformé, vous avez l'avantage sur les vérifications de Sagesse.</p>",
      "chat": "",
      "unidentified": ""
    },
    "source": "Eberron",
    "activation": {
      "type": "",
      "cost": 0,
      "condition": ""
    },
    "duration": {
      "value": null,
      "units": ""
    },
    "target": {
      "value": null,
      "width": null,
      "units": "",
      "type": ""
    },
    "range": {
      "value": null,
      "long": null,
      "units": ""
    },
    "uses": {
      "value": null,
      "max": "",
      "per": null
    },
    "consume": {
      "type": "",
      "target": null,
      "amount": null
    },
    "ability": null,
    "actionType": "",
    "attackBonus": 0,
    "chatFlavor": "",
    "critical": {
      "threshold": null,
      "damage": ""
    },
    "damage": {
      "parts": [],
      "versatile": ""
    },
    "formula": "",
    "save": {
      "ability": "",
      "dc": null,
      "scaling": "spell"
    },
    "requirements": "Shifter",
    "recharge": {
      "value": null,
      "charged": false
    }
  },
  "_key": "!items!4dCFhbFdRyzMpLzM"
}