{
  "name": "Crown of Stars",
  "type": "spell",
  "img": "icons/magic/control/control-influence-crown-yellow.webp",
  "effects": [],
  "flags": {
    "srd5e": {
      "page": "spells.html",
      "source": "XGE",
      "hash": "crown%20of%20stars_xge",
      "propDroppable": "spell"
    },
    "core": {
      "sourceId": "Item.Ve1j1GxH5MSJ51Pn"
    },
    "rest-recovery": {
      "data": {
        "recovery": {
          "enabled": false
        }
      }
    }
  },
  "system": {
    "description": {
      "value": "<div class=\"rd__b  rd__b--3\"><p>Sept étincelles lumineuses en forme d'étoiles apparaissent et orbitent autour de votre tête jusqu'à la fin du sort. Vous pouvez utiliser une action bonus pour envoyer l'une des étincelles vers une créature ou un objet à 36.576 mètres de vous. Lorsque vous faites cela, effectuez une attaque de sort à distance. En cas de réussite, la cible subit [[/r 4d12]] dégâts radiants. Que vous touchiez ou manquiez la cible, l'étincelle est dépensée. Le sort se termine prématurément si vous dépensez la dernière étincelle.</p><p>Si vous avez quatre étincelles ou plus, elles émettent une lumière vive dans un rayon de 9.144 mètres et une lumière faible pour 9.144 mètres supplémentaires. Si vous avez une à trois étincelles, elles émettent une lumière faible dans un rayon de 9.144 mètres.</p></div><div class=\"rd__b  rd__b--3\"><div class=\"rd__b  rd__b--3\"><h3><span class=\"entry-title-inner\">À des niveaux supérieurs</span></h3><p>Lorsque vous lancez ce sort en utilisant une emplacement de sort de niveau 8 ou supérieur, le nombre d'étincelles créées augmente de deux pour chaque niveau d'emplacement au-dessus du 7e.</p><p><strong>Listes de sorts.</strong> @UUID[Compendium.5e-complete-fr.5e-journals.7iH4qANs2gxn0MIs.JournalEntryPage.NX28XQnco4pjOzF6]{Sorcerer}, @UUID[Compendium.5e-complete-fr.5e-journals.7iH4qANs2gxn0MIs.JournalEntryPage.JsbrmCx9VF1Sizn8]{Warlock}, @UUID[Compendium.5e-complete-fr.5e-journals.7iH4qANs2gxn0MIs.JournalEntryPage.5YX3k6END6NQWHOB]{Wizard}</p></div></div>",
      "chat": "",
      "unidentified": ""
    },
    "source": "XGE",
    "activation": {
      "type": "action",
      "cost": 1,
      "condition": ""
    },
    "duration": {
      "value": 1,
      "units": "hour"
    },
    "target": {
      "value": null,
      "width": null,
      "units": "",
      "type": "self"
    },
    "range": {
      "value": 37,
      "long": null,
      "units": "m"
    },
    "uses": {
      "value": null,
      "max": "",
      "per": "",
      "recovery": ""
    },
    "consume": {
      "type": "",
      "target": "",
      "amount": null
    },
    "ability": "",
    "actionType": "rsak",
    "attackBonus": "",
    "chatFlavor": "",
    "critical": {
      "threshold": null,
      "damage": ""
    },
    "damage": {
      "parts": [
        [
          "4d12",
          "radiant"
        ]
      ],
      "versatile": ""
    },
    "formula": "",
    "save": {
      "ability": "",
      "dc": null,
      "scaling": "spell"
    },
    "level": 7,
    "school": "evo",
    "components": {
      "value": "",
      "vocal": true,
      "somatic": true,
      "material": false,
      "ritual": false,
      "concentration": false
    },
    "materials": {
      "value": "",
      "consumed": false,
      "cost": 0,
      "supply": 0
    },
    "preparation": {
      "mode": "prepared",
      "prepared": false
    },
    "scaling": {
      "mode": "none",
      "formula": ""
    }
  },
  "ownership": {
    "default": 0,
    "UjfixXuqstXNdypa": 3,
    "KEn0n6JsNNAtXIka": 3
  },
  "_stats": {
    "systemId": "dnd5e",
    "systemVersion": "2.0.3",
    "coreVersion": "12.331",
    "createdTime": 1665649060037,
    "modifiedTime": 1668192331274,
    "lastModifiedBy": "EHpONhziSoZpUpN3",
    "compendiumSource": "Item.Ve1j1GxH5MSJ51Pn",
    "duplicateSource": null
  },
  "folder": null,
  "sort": 0,
  "_id": "jiLdjs20lNYSmmw9",
  "_key": "!items!jiLdjs20lNYSmmw9"
}