{
  "_id": "StNXJMU3vcM9fKrA",
  "name": "Evard's Black Tentacles",
  "type": "spell",
  "img": "icons/creatures/tentacles/tentacles-octopus-black-pink.webp",
  "effects": [],
  "folder": null,
  "sort": 0,
  "flags": {
    "betterRolls5e": {
      "critRange": {
        "type": "String",
        "value": null
      },
      "critDamage": {
        "type": "String",
        "value": ""
      },
      "quickDesc": {
        "type": "Boolean",
        "value": true,
        "altValue": true
      },
      "quickAttack": {
        "type": "Boolean",
        "value": true,
        "altValue": true
      },
      "quickSave": {
        "type": "Boolean",
        "value": true,
        "altValue": true
      },
      "quickDamage": {
        "type": "Array",
        "value": [
          true
        ],
        "altValue": [
          true
        ],
        "context": {
          "0": ""
        }
      },
      "quickVersatile": {
        "type": "Boolean",
        "value": false,
        "altValue": false
      },
      "quickProperties": {
        "type": "Boolean",
        "value": true,
        "altValue": true
      },
      "quickCharges": {
        "type": "Boolean",
        "value": {
          "use": true,
          "resource": true
        },
        "altValue": {
          "use": true,
          "resource": true
        }
      },
      "quickTemplate": {
        "type": "Boolean",
        "value": true,
        "altValue": true
      },
      "quickOther": {
        "type": "Boolean",
        "value": true,
        "altValue": true,
        "context": ""
      },
      "quickFlavor": {
        "type": "Boolean",
        "value": true,
        "altValue": true
      },
      "quickPrompt": {
        "type": "Boolean",
        "value": false,
        "altValue": false
      }
    },
    "core": {
      "sourceId": "Item.jn9DrPgW7CG2si1x"
    },
    "mre-dnd5e": {
      "formulaGroups": [
        {
          "label": "Primary",
          "formulaSet": [
            0
          ]
        }
      ]
    }
  },
  "system": {
    "description": {
      "value": "<p>Des tentacules d'ébène ondulants remplissent un carré de 6 mètres au sol que vous pouvez voir à portée. Pour la durée, ces tentacules transforment le sol dans la zone en terrain difficile.</p>\n<p>Lorsque une créature entre dans la zone affectée pour la première fois lors d'un tour ou commence son tour là-bas, la créature doit réussir un jet de sauvegarde de Dextérité ou subir 3d6 dégâts contondants et être immobilisée par les tentacules jusqu'à la fin du sort. Une créature qui commence son tour dans la zone et est déjà immobilisée par les tentacules subit 3d6 dégâts contondants.</p>\n<p>Une créature immobilisée par les tentacules peut utiliser son action pour faire un jet de Force ou de Dextérité (à son choix) contre votre DC de sauvegarde de sort. En cas de succès, elle se libère.</p>\n<p><strong>Spell Lists.</strong> Wizard</p>",
      "chat": "",
      "unidentified": ""
    },
    "source": "PHB",
    "activation": {
      "type": "action",
      "cost": 1,
      "condition": ""
    },
    "duration": {
      "value": 1,
      "units": "minute"
    },
    "target": {
      "value": 6,
      "width": null,
      "units": "m",
      "type": "square"
    },
    "range": {
      "value": 27,
      "long": null,
      "units": "m"
    },
    "uses": {
      "value": 0,
      "max": "0",
      "per": "",
      "recovery": ""
    },
    "consume": {
      "type": "",
      "target": "",
      "amount": null
    },
    "ability": "",
    "actionType": "save",
    "attackBonus": 0,
    "chatFlavor": "",
    "critical": {
      "threshold": null,
      "damage": null
    },
    "damage": {
      "parts": [
        [
          "3d6",
          "bludgeoning"
        ]
      ],
      "versatile": ""
    },
    "formula": "",
    "save": {
      "ability": "dex",
      "dc": null,
      "scaling": "spell"
    },
    "level": 4,
    "school": "con",
    "components": {
      "value": "",
      "vocal": true,
      "somatic": true,
      "material": true,
      "ritual": false,
      "concentration": true
    },
    "materials": {
      "value": "A piece of tentacle from a giant octopus or a giant squid",
      "consumed": false,
      "cost": 0,
      "supply": 0
    },
    "preparation": {
      "mode": "prepared",
      "prepared": false
    },
    "scaling": {
      "mode": "none",
      "formula": ""
    }
  },
  "ownership": {
    "default": 0,
    "LCw1mxC8S2Al3dWA": 3
  },
  "_stats": {
    "systemId": "dnd5e",
    "systemVersion": "2.0.3",
    "coreVersion": "12.331",
    "createdTime": null,
    "modifiedTime": 1664757993949,
    "lastModifiedBy": "WaZ5phMRyaHwTSEz",
    "compendiumSource": "Item.jn9DrPgW7CG2si1x",
    "duplicateSource": null
  },
  "_key": "!items!StNXJMU3vcM9fKrA"
}