{
  "name": "Passwall",
  "type": "spell",
  "img": "icons/commodities/stone/paver-brick-blue.webp",
  "effects": [],
  "folder": null,
  "sort": 0,
  "flags": {
    "core": {
      "sourceId": "Compendium.world.spells-expanded.d9MwcXi7Il3HROXd"
    }
  },
  "_id": "oohRV7SnACkrS3ts",
  "system": {
    "description": {
      "value": "<p>Un passage apparaît à un point de votre choix que vous pouvez voir sur une surface en bois, en plâtre ou en pierre (comme un mur, un plafond ou un sol) à portée, et dure pendant la durée. Vous choisissez les dimensions de l'ouverture : jusqu'à 5 pieds de large, 8 pieds de haut et 20 pieds de profondeur. Le passage ne crée aucune instabilité dans la structure qui l'entoure.</p><p>Lorsque l'ouverture disparaît, toute créature ou objet encore dans le passage créé par le sort est éjecté en toute sécurité vers un espace inoccupé le plus proche de la surface sur laquelle vous avez lancé le sort.</p>",
      "chat": "",
      "unidentified": ""
    },
    "source": "PHB",
    "activation": {
      "type": "action",
      "cost": 1,
      "condition": ""
    },
    "duration": {
      "value": 1,
      "units": "hour"
    },
    "target": {
      "value": null,
      "width": null,
      "units": "any",
      "type": "space"
    },
    "range": {
      "value": 30,
      "long": 0,
      "units": "ft"
    },
    "uses": {
      "value": 0,
      "max": "0",
      "per": "",
      "recovery": ""
    },
    "consume": {
      "type": "",
      "target": "",
      "amount": null
    },
    "ability": "",
    "actionType": "util",
    "attackBonus": 0,
    "chatFlavor": "",
    "critical": {
      "threshold": null,
      "damage": null
    },
    "damage": {
      "parts": [],
      "versatile": "",
      "value": ""
    },
    "formula": "",
    "save": {
      "ability": "",
      "dc": null,
      "scaling": "spell",
      "value": ""
    },
    "level": 5,
    "school": "trs",
    "components": {
      "value": "",
      "vocal": true,
      "somatic": true,
      "material": true,
      "ritual": false,
      "concentration": false
    },
    "materials": {
      "value": "A pinch of sesame seeds",
      "consumed": false,
      "cost": 0,
      "supply": 0
    },
    "preparation": {
      "mode": "prepared",
      "prepared": false
    },
    "scaling": {
      "mode": "none",
      "formula": ""
    }
  },
  "ownership": {
    "default": 0,
    "LCw1mxC8S2Al3dWA": 3
  },
  "_stats": {
    "systemId": "dnd5e",
    "systemVersion": "2.0.3",
    "coreVersion": "12.331",
    "createdTime": null,
    "modifiedTime": 1664780970043,
    "lastModifiedBy": "UjfixXuqstXNdypa",
    "compendiumSource": "Compendium.world.spells-expanded.d9MwcXi7Il3HROXd",
    "duplicateSource": null
  },
  "_key": "!items!oohRV7SnACkrS3ts"
}
