{
  "name": "Tsunami",
  "type": "spell",
  "img": "icons/magic/water/wave-water-blue.webp",
  "system": {
    "description": {
      "value": "<p>Un mur d'eau apparaît à un point de votre choix dans la portée. Vous pouvez faire le mur jusqu'à 300 pieds de long, 300 pieds de haut et 50 pieds d'épaisseur. Le mur dure pendant la durée.</p><p>Lorsque le mur apparaît, chaque créature dans sa zone doit faire un jet de sauvegarde de Force. En cas d'échec, une créature subit [[/r 6d10]] dégâts contondants, ou la moitié des dégâts en cas de réussite.</p><p>Au début de chacun de vos tours après l'apparition du mur, le mur, ainsi que toute créature en lui, se déplace de 50 pieds loin de vous. Toute créature Géante ou plus petite à l'intérieur du mur ou dont l'espace est traversé par le mur lorsqu'il se déplace doit réussir un jet de sauvegarde de Force ou subir [[/r 5d10]] dégâts contondants. Une créature ne peut subir ces dégâts qu'une fois par round. À la fin du tour, la hauteur du mur est réduite de 50 pieds, et les dégâts que les créatures subissent du sort lors des rounds suivants sont réduits de [[/r 1d10]]. Lorsque le mur atteint 0 pieds de hauteur, le sort se termine.</p><p>Une créature prise dans le mur peut se déplacer en nageant. En raison de la force de la vague, la créature doit toutefois réussir un jet de Force (<strong>Athletics</strong>) contre votre DC de sauvegarde de sort pour se déplacer. Si elle échoue au jet, elle ne peut pas se déplacer. Une créature qui sort de la zone tombe au sol.</p><p><strong>Spell Lists.</strong> Druid</p>",
      "chat": "",
      "unidentified": ""
    },
    "source": "PHB",
    "activation": {
      "type": "minute",
      "cost": 1,
      "condition": ""
    },
    "duration": {
      "value": 6,
      "units": "round"
    },
    "target": {
      "value": 91,
      "width": 50,
      "units": "m",
      "type": "wall"
    },
    "range": {
      "value": null,
      "long": null,
      "units": "any"
    },
    "uses": {
      "value": null,
      "max": "",
      "per": "",
      "recovery": ""
    },
    "consume": {
      "type": "",
      "target": "",
      "amount": null
    },
    "ability": "",
    "actionType": "save",
    "attackBonus": 0,
    "chatFlavor": "",
    "critical": {
      "threshold": null,
      "damage": ""
    },
    "damage": {
      "parts": [
        [
          "6d10",
          "bludgeoning"
        ],
        [
          "5d10",
          "bludgeoning"
        ],
        [
          "4d10",
          "bludgeoning"
        ],
        [
          "3d10",
          "bludgeoning"
        ],
        [
          "2d10",
          "bludgeoning"
        ],
        [
          "1d10",
          "bludgeoning"
        ]
      ],
      "versatile": ""
    },
    "formula": "",
    "save": {
      "ability": "",
      "dc": null,
      "scaling": "spell"
    },
    "level": 8,
    "school": "con",
    "components": {
      "value": "",
      "vocal": true,
      "somatic": true,
      "material": false,
      "ritual": false,
      "concentration": true
    },
    "materials": {
      "value": "",
      "consumed": false,
      "cost": 0,
      "supply": 0
    },
    "preparation": {
      "mode": "prepared",
      "prepared": false
    },
    "scaling": {
      "mode": "none",
      "formula": ""
    }
  },
  "effects": [],
  "ownership": {
    "default": 0,
    "KEn0n6JsNNAtXIka": 3
  },
  "flags": {
    "core": {
      "sourceId": "Item.7VLcUsARLAxlBoHd"
    },
    "rest-recovery": {
      "data": {
        "recovery": {
          "enabled": false
        }
      }
    },
    "rollgroups": {
      "config": {
        "groups": [
          {
            "label": "Round 1",
            "parts": [
              0
            ]
          },
          {
            "label": "Round 2",
            "parts": [
              1
            ]
          },
          {
            "label": "Round 3",
            "parts": [
              2
            ]
          },
          {
            "label": "Round 4",
            "parts": [
              3
            ]
          },
          {
            "label": "Round 5",
            "parts": [
              4
            ]
          },
          {
            "label": "Round 6",
            "parts": [
              5
            ]
          }
        ]
      }
    }
  },
  "_stats": {
    "systemId": "dnd5e",
    "systemVersion": "2.0.3",
    "coreVersion": "12.331",
    "createdTime": 1665730090908,
    "modifiedTime": 1667347276686,
    "lastModifiedBy": "EHpONhziSoZpUpN3",
    "compendiumSource": "Item.7VLcUsARLAxlBoHd",
    "duplicateSource": null
  },
  "folder": null,
  "sort": 0,
  "_id": "slHvEvE5CHpZiwzb",
  "_key": "!items!slHvEvE5CHpZiwzb"
}