{
  "name": "Tentacle Disease",
  "type": "feat",
  "img": "icons/magic/acid/projectile-glowing-bubbles.webp",
  "effects": [],
  "folder": null,
  "sort": 0,
  "flags": {
    "core": {
      "sourceId": "Compendium.dnd5e.monsterfeatures.y18y37F8ppFLGuLb"
    }
  },
  "_id": "D58MOdTtfv7NX0Y6",
  "_stats": {
    "coreVersion": "12.331",
    "systemId": null,
    "systemVersion": null,
    "createdTime": null,
    "modifiedTime": null,
    "lastModifiedBy": null,
    "compendiumSource": null,
    "duplicateSource": null
  },
  "ownership": {
    "default": 0,
    "4lCdaYwhvK1T68Lv": 3
  },
  "system": {
    "description": {
      "value": "<section class=\"secret\">\n<p><strong>Après 1 minute</strong>, la peau de la créature malade devient translucide et visqueuse, la créature ne peut pas récupérer des points de vie à moins d'être sous l'eau, et la maladie ne peut être enlevée que par un sort de guérison ou un autre sort de guérison de maladie de niveau 6 ou supérieur. Lorsque la créature est <strong>en dehors d'une étendue d'eau</strong>, elle subit <strong>6 (1d12) dégâts d'acide toutes les 10 minutes</strong> à moins que de l'humidité soit appliquée sur la peau avant que 10 minutes ne se soient écoulées.</p>\n</section>\n<p>Vous ressentez une douleur fulgurante qui traverse votre corps !</p>",
      "chat": "",
      "unidentified": ""
    },
    "source": "MM pg. 13",
    "activation": {
      "type": "none",
      "cost": 0,
      "condition": ""
    },
    "duration": {
      "value": null,
      "units": ""
    },
    "target": {
      "value": null,
      "width": null,
      "units": "",
      "type": ""
    },
    "range": {
      "value": null,
      "long": null,
      "units": ""
    },
    "uses": {
      "value": 0,
      "max": 0,
      "per": ""
    },
    "consume": {
      "type": "",
      "target": "",
      "amount": null
    },
    "ability": "",
    "actionType": "other",
    "attackBonus": 0,
    "chatFlavor": "",
    "critical": {
      "threshold": null,
      "damage": ""
    },
    "damage": {
      "parts": [],
      "versatile": ""
    },
    "formula": "",
    "save": {
      "ability": "",
      "dc": null,
      "scaling": "spell"
    },
    "requirements": "",
    "recharge": {
      "value": null,
      "charged": false
    },
    "featType": {
      "value": "",
      "_deprecated": true
    },
    "time": {
      "value": "",
      "_deprecated": true
    },
    "damageType": {
      "value": "",
      "_deprecated": true
    }
  },
  "_key": "!items!D58MOdTtfv7NX0Y6"
}
