{
  "_id": "aqbWkr7ooNTId8WX",
  "name": "The Celestial",
  "type": "subclass",
  "img": "icons/magic/nature/symbol-sun-yellow.webp",
  "effects": [],
  "folder": null,
  "sort": 0,
  "flags": {
    "mre-dnd5e": {
      "formulaGroups": [
        {
          "label": "Primary",
          "formulaSet": []
        }
      ]
    },
    "core": {
      "sourceId": "Item.1df58paWoDHOSO6H"
    }
  },
  "system": {
    "description": {
      "value": "<p>Votre patron est un être puissant des Plans Supérieurs. Vous vous êtes lié à un empyréen antique, solaire, ki-rin, licorne, ou autre entité qui réside dans les plans de la félicité éternelle. Votre pacte avec cet être vous permet de ressentir la plus infime caresse de la lumière sainte qui illumine le multivers.</p>\n<p>Être connecté à un tel pouvoir peut provoquer des changements dans votre comportement et vos croyances. Vous pourriez vous retrouver poussé à annihiler les morts-vivants, à vaincre les démons, et à protéger les innocents. Parfois, votre cœur pourrait aussi être rempli d'un désir pour le royaume céleste de votre patron, un désir de vagabonder dans ce paradis pour le reste de vos jours. Mais vous savez que votre mission est parmi les mortels pour l'instant et que votre pacte vous lie à apporter de la lumière aux endroits sombres du monde.</p>\n<h3>Les Caractéristiques Célestes</h3>\n<p>1er Niveau : @Compendium[5e-complete-fr.5e-class-features.v55bDYCqQjPcJkaC]{Expanded Spells}, @Compendium[5e-complete-fr.5e-class-features.jD11TnJ7woJLi1z4]{Bonus Cantrips}, @Compendium[5e-complete-fr.5e-class-features.fOwH6QA8RmucSj3I]{Healing Light}</p>\n<p>6e Niveau : @Compendium[5e-complete-fr.5e-class-features.HDVQV7Gn8iwyaB8D]{Radiant Soul}</p>\n<p>10e Niveau : @Compendium[5e-complete-fr.5e-class-features.EAwAyIkaVDZDeS2w]{Celestial Resistance}</p>\n<p>14e Niveau : @Compendium[5e-complete-fr.5e-class-features.K7jC4fKeezGA52Fy]{Searing Vengeance}</p>",
      "chat": "",
      "unidentified": ""
    },
    "source": "XGE",
    "identifier": "the-celestial",
    "classIdentifier": "warlock",
    "advancement": [
      {
        "_id": "xnxccycfeefnouqy",
        "type": "ItemGrant",
        "configuration": {
          "items": [
            "Compendium.5e-complete-fr.5e-class-features.v55bDYCqQjPcJkaC",
            "Compendium.5e-complete-fr.5e-class-features.jD11TnJ7woJLi1z4",
            "Compendium.5e-complete-fr.5e-class-features.fOwH6QA8RmucSj3I",
            "Compendium.5e-complete-fr.5e-spells.thAAdZnGrQEvOAE6",
            "Compendium.5e-complete-fr.5e-spells.wTzLu39LWvy36qpj"
          ],
          "optional": false,
          "spell": {
            "ability": "",
            "preparation": "always",
            "uses": {
              "max": "",
              "per": ""
            }
          }
        },
        "value": {},
        "level": 1,
        "title": "The Celestial Features and Spells",
        "icon": ""
      },
      {
        "_id": "p8i735e5gf37wq2k",
        "type": "ItemGrant",
        "configuration": {
          "items": [
            "Compendium.5e-complete-fr.5e-class-features.HDVQV7Gn8iwyaB8D"
          ],
          "optional": false
        },
        "value": {},
        "level": 6,
        "title": "The Celestial Feature",
        "icon": ""
      },
      {
        "_id": "j3clm904r7rqo7yz",
        "type": "ItemGrant",
        "configuration": {
          "items": [
            "Compendium.5e-complete-fr.5e-class-features.EAwAyIkaVDZDeS2w"
          ],
          "optional": false
        },
        "value": {},
        "level": 10,
        "title": "The Celestial Feature",
        "icon": ""
      },
      {
        "_id": "ljg8dh3xuzlrkxbd",
        "type": "ItemGrant",
        "configuration": {
          "items": [
            "Compendium.5e-complete-fr.5e-class-features.K7jC4fKeezGA52Fy"
          ],
          "optional": false
        },
        "value": {},
        "level": 13,
        "title": "The Celestial Feature",
        "icon": ""
      }
    ],
    "spellcasting": {
      "progression": "none",
      "ability": ""
    }
  },
  "ownership": {
    "default": 0,
    "UjfixXuqstXNdypa": 3
  },
  "_stats": {
    "systemId": "dnd5e",
    "systemVersion": "2.0.3",
    "coreVersion": "12.331",
    "createdTime": null,
    "modifiedTime": 1667803851162,
    "lastModifiedBy": "EHpONhziSoZpUpN3",
    "compendiumSource": "Item.1df58paWoDHOSO6H",
    "duplicateSource": null
  },
  "_key": "!items!aqbWkr7ooNTId8WX"
}