{
  "name": "The Hexblade",
  "type": "subclass",
  "img": "icons/weapons/swords/sword-runed-glowing.webp",
  "effects": [],
  "folder": null,
  "sort": 0,
  "flags": {
    "mre-dnd5e": {
      "formulaGroups": [
        {
          "label": "Primary",
          "formulaSet": []
        }
      ]
    },
    "core": {
      "sourceId": "Item.I80Z7FXWu0V9hfKc"
    }
  },
  "_id": "v5CCqWqWZYi8zh6B",
  "_stats": {
    "coreVersion": "12.331",
    "systemId": null,
    "systemVersion": null,
    "createdTime": null,
    "modifiedTime": null,
    "lastModifiedBy": null,
    "compendiumSource": null,
    "duplicateSource": null
  },
  "ownership": {
    "default": 0,
    "UjfixXuqstXNdypa": 3
  },
  "system": {
    "description": {
      "value": "<p>Vous avez conclu un pacte avec une entité mystérieuse du Shadowfell – une force qui se manifeste sous la forme d'armes magiques sentientes sculptées dans la substance de l'ombre. L'épée puissante Blackrazor est la plus notable de ces armes, qui ont été dispersées à travers le multivers au fil des âges. La force ombreuse derrière ces armes peut offrir du pouvoir aux warlocks qui forment des pactes avec elle. De nombreux hexblade warlocks créent des armes qui imitent celles formées dans le Shadowfell. D'autres se passent de telles armes, se contentant d'entrelacer la magie sombre de ce plan dans leur lancer de sorts.</p>\n<p>Parce que la Raven Queen est connue pour avoir forgé la première de ces armes, de nombreux sages spéculent qu'elle et la force ne font qu'un et que les armes, ainsi que les hexblade warlocks, sont des outils qu'elle utilise pour manipuler les événements sur le Plan Matériel à ses fins insondables.</p>\n<h3>The Hexblade Features</h3>\n<p>1st Level:  @Compendium[5e-complete-fr.5e-class-features.zXuH9wmn9UAscGWp]{Expanded Spells},  @Compendium[5e-complete-fr.5e-class-features.R7KO3rSiHZMJIyfX]{Hexblade's Curse},  @Compendium[5e-complete-fr.5e-class-features.UCpwaFuHJhHLx0ti]{Hex Warrior}</p>\n<p>6th Level:  @Compendium[5e-complete-fr.5e-class-features.LOwv1s3tu2a6vR2C]{Accursed Specter}</p>\n<p>10th Level:  @Compendium[5e-complete-fr.5e-class-features.j2rzVMZv6TRmqrKR]{Armor of Hexes}</p>\n<p>14th Level:  @Compendium[5e-complete-fr.5e-class-features.eXp3ZAp07obpS8mj]{Master of Hexes}</p>",
      "chat": "",
      "unidentified": ""
    },
    "source": "XGE",
    "identifier": "the-hexblade",
    "classIdentifier": "warlock",
    "advancement": [
      {
        "_id": "trq283g1wpn4wo5d",
        "type": "ItemGrant",
        "configuration": {
          "items": [
            "Compendium.5e-complete-fr.5e-class-features.zXuH9wmn9UAscGWp",
            "Compendium.5e-complete-fr.5e-class-features.R7KO3rSiHZMJIyfX",
            "Compendium.5e-complete-fr.5e-class-features.UCpwaFuHJhHLx0ti"
          ],
          "optional": false
        },
        "value": {},
        "level": 1,
        "title": "The Hexblade Features",
        "icon": ""
      },
      {
        "_id": "4zftbyxembiopwnw",
        "type": "ItemGrant",
        "configuration": {
          "items": [
            "Compendium.5e-complete-fr.5e-class-features.LOwv1s3tu2a6vR2C"
          ],
          "optional": false
        },
        "value": {},
        "level": 6,
        "title": "The Hexblade Feature",
        "icon": ""
      },
      {
        "_id": "kl4u2rn82mcpsvcs",
        "type": "ItemGrant",
        "configuration": {
          "items": [
            "Compendium.5e-complete-fr.5e-class-features.j2rzVMZv6TRmqrKR"
          ],
          "optional": false
        },
        "value": {},
        "level": 9,
        "title": "The Hexblade Feature",
        "icon": ""
      },
      {
        "_id": "y4y0r3ewdlz132v6",
        "type": "ItemGrant",
        "configuration": {
          "items": [
            "Compendium.5e-complete-fr.5e-class-features.eXp3ZAp07obpS8mj"
          ],
          "optional": false
        },
        "value": {},
        "level": 14,
        "title": "The Hexblade Feature",
        "icon": ""
      }
    ],
    "spellcasting": {
      "progression": "none",
      "ability": ""
    }
  },
  "_key": "!items!v5CCqWqWZYi8zh6B"
}
