{
  "_id": "ylODggG5SlKVKMjj",
  "name": "Crusher",
  "type": "feat",
  "img": "icons/weapons/hammers/hammer-double-glowing-yellow.webp",
  "effects": [],
  "folder": null,
  "sort": 0,
  "flags": {
    "mre-dnd5e": {
      "formulaGroups": [
        {
          "label": "Primary",
          "formulaSet": []
        }
      ]
    },
    "magicitems": {
      "enabled": false,
      "equipped": false,
      "attuned": false,
      "charges": "0",
      "chargeType": "c1",
      "destroy": false,
      "destroyFlavorText": "reaches 0 charges: it crumbles into ashes and is destroyed.",
      "rechargeable": false,
      "recharge": "0",
      "rechargeType": "t1",
      "rechargeUnit": "r1",
      "sorting": "l"
    },
    "core": {
      "sourceId": "Item.NHubaczztUoh2zUk"
    }
  },
  "system": {
    "description": {
      "value": "<p>Vous êtes pratiqué dans l'art de broyer vos ennemis, ce qui vous accorde les avantages suivants:</p>\n<ul>\n<li>Augmentez votre Force ou votre Constitution de 1, jusqu'à un maximum de 20.</li>\n<li>Une fois par tour, lorsque vous touchez une créature avec une attaque qui inflige des dégâts contondants, vous pouvez la déplacer de 2 mètres vers un espace inoccupé, à condition que la cible ne soit pas plus grande d'une taille que vous.</li>\n<li>Lorsque vous obtenez un coup critique qui inflige des dégâts contondants à une créature, les jets d'attaque contre cette créature sont réalisés avec <strong>advantage</strong> jusqu'au début de votre prochain tour.</li>\n</ul>",
      "chat": "",
      "unidentified": ""
    },
    "source": "TCE",
    "activation": {
      "type": "",
      "cost": 0,
      "condition": ""
    },
    "duration": {
      "value": null,
      "units": ""
    },
    "target": {
      "value": null,
      "width": null,
      "units": "",
      "type": ""
    },
    "range": {
      "value": null,
      "long": null,
      "units": ""
    },
    "uses": {
      "value": null,
      "max": "",
      "per": null,
      "recovery": ""
    },
    "consume": {
      "type": "",
      "target": null,
      "amount": null
    },
    "ability": null,
    "actionType": "",
    "attackBonus": 0,
    "chatFlavor": "",
    "critical": {
      "threshold": null,
      "damage": ""
    },
    "damage": {
      "parts": [],
      "versatile": ""
    },
    "formula": "",
    "save": {
      "ability": "",
      "dc": null,
      "scaling": "spell"
    },
    "requirements": "Feat",
    "recharge": {
      "value": null,
      "charged": false
    }
  },
  "ownership": {
    "default": 0,
    "rB1eq1YiygSNB2xV": 3
  },
  "_stats": {
    "systemId": "dnd5e",
    "systemVersion": "2.0.3",
    "coreVersion": "12.331",
    "createdTime": null,
    "modifiedTime": 1667807579623,
    "lastModifiedBy": "EHpONhziSoZpUpN3",
    "compendiumSource": "Item.NHubaczztUoh2zUk",
    "duplicateSource": null
  },
  "_key": "!items!ylODggG5SlKVKMjj"
}