{
  "_id": "OxioCm9UByLX9jzg",
  "name": "Bead of Force",
  "type": "consumable",
  "img": "icons/magic/water/orb-ice-opaque.webp",
  "effects": [],
  "folder": null,
  "sort": 0,
  "flags": {
    "core": {
      "sourceId": "Compendium.dnd5e.items.SqTtbBCfiEsmZ36N"
    },
    "mre-dnd5e": {
      "formulaGroups": [
        {
          "label": "Primary",
          "formulaSet": []
        }
      ]
    },
    "magicitems": {
      "enabled": false,
      "equipped": false,
      "attuned": false,
      "charges": "0",
      "chargeType": "c1",
      "destroy": false,
      "destroyFlavorText": "reaches 0 charges: it crumbles into ashes and is destroyed.",
      "rechargeable": false,
      "recharge": "0",
      "rechargeType": "t1",
      "rechargeUnit": "r1",
      "sorting": "l"
    }
  },
  "_stats": {
    "coreVersion": "12.331",
    "systemId": null,
    "systemVersion": null,
    "createdTime": null,
    "modifiedTime": null,
    "lastModifiedBy": null,
    "compendiumSource": null,
    "duplicateSource": null
  },
  "ownership": {
    "default": 0,
    "4lCdaYwhvK1T68Lv": 3
  },
  "system": {
    "description": {
      "value": "<p><em>Objet merveilleux</em></p>\n<p>Cette petite sphère noire mesure 3/4 de pouce de diamètre et pèse une once. En général, 1d4 + 4 Perles de Force sont trouvées ensemble.</p>\n<p>Vous pouvez utiliser une action pour lancer la perle jusqu'à 60 pieds. La perle explose à l'impact et est détruite. Chaque créature dans un rayon de 10 pieds de l'endroit où la perle est tombée doit réussir un jet de sauvegarde de Dexterité DC 15 ou subir 5d4 dégâts de force. Une sphère de force transparente enferme alors la zone pendant 1 minute. Toute créature qui a échoué au jet de sauvegarde et est complètement à l'intérieur de la zone est piégée à l'intérieur de cette sphère. Les créatures qui ont réussi le jet de sauvegarde, ou sont partiellement à l'intérieur de la zone, sont repoussées du centre de la sphère jusqu'à ce qu'elles ne soient plus à l'intérieur. Seule l'air respirable peut traverser la paroi de la sphère. Aucune attaque ou autre effet ne peut.</p>\n<p>Une créature enfermée peut utiliser son action pour pousser contre la paroi de la sphère, déplaçant la sphère jusqu'à la moitié de la vitesse de déplacement de la créature. La sphère peut être ramassée, et sa magie la fait peser seulement 1 livre, quelle que soit le poids des créatures à l'intérieur.</p>",
      "chat": "",
      "unidentified": ""
    },
    "source": "DMG",
    "quantity": 1,
    "weight": 0.06,
    "price": "960",
    "attunement": 0,
    "equipped": false,
    "rarity": "rare",
    "identified": true,
    "activation": {
      "type": "action",
      "cost": 1,
      "condition": ""
    },
    "duration": {
      "value": 1,
      "units": "minute"
    },
    "target": {
      "value": 10,
      "width": null,
      "units": "ft",
      "type": "radius"
    },
    "range": {
      "value": 60,
      "long": 0,
      "units": "ft"
    },
    "uses": {
      "value": 1,
      "max": "1",
      "per": "charges",
      "autoDestroy": true,
      "autoUse": true
    },
    "consume": {
      "type": "",
      "target": "",
      "amount": null
    },
    "ability": "",
    "actionType": "save",
    "attackBonus": 0,
    "chatFlavor": "",
    "critical": {
      "threshold": null,
      "damage": ""
    },
    "damage": {
      "parts": [],
      "versatile": ""
    },
    "formula": "5d4",
    "save": {
      "ability": "dex",
      "dc": 15,
      "scaling": "flat"
    },
    "consumableType": "trinket"
  },
  "_key": "!items!OxioCm9UByLX9jzg"
}
