{
  "name": "Handaxe +3",
  "type": "weapon",
  "img": "icons/weapons/axes/axe-broad-black.webp",
  "effects": [],
  "folder": null,
  "sort": 0,
  "flags": {
    "core": {
      "sourceId": "Compendium.dnd5e.items.cmnBssaWWzWWm70C"
    }
  },
  "_id": "A41W3rfC7zyb6WJp",
  "_stats": {
    "coreVersion": "12.331",
    "systemId": null,
    "systemVersion": null,
    "createdTime": null,
    "modifiedTime": null,
    "lastModifiedBy": null,
    "compendiumSource": null,
    "duplicateSource": null
  },
  "ownership": {
    "default": 0,
    "4lCdaYwhvK1T68Lv": 3
  },
  "system": {
    "description": {
      "value": "<p><em>Que ce soit par bénédiction démoniaque, don céleste, expérience démente, ou artisanat habile, cette arme a été améliorée pour causer plus d'effusion de sang par son porteur.</em></p>\n<p>Vous avez un bonus aux jets d'attaque et de dégâts effectués avec cette arme magique.</p>",
      "chat": "",
      "unidentified": ""
    },
    "source": "DMG pg. 213",
    "quantity": 1,
    "weight": 2,
    "price": 16000,
    "attunement": 0,
    "equipped": false,
    "rarity": "veryRare",
    "identified": true,
    "activation": {
      "type": "action",
      "cost": 1,
      "condition": ""
    },
    "duration": {
      "value": null,
      "units": ""
    },
    "target": {
      "value": null,
      "width": null,
      "units": "",
      "type": ""
    },
    "range": {
      "value": 20,
      "long": 60,
      "units": "ft"
    },
    "uses": {
      "value": null,
      "max": "",
      "per": ""
    },
    "consume": {
      "type": "",
      "target": null,
      "amount": null
    },
    "ability": null,
    "actionType": "mwak",
    "attackBonus": 3,
    "chatFlavor": "",
    "critical": {
      "threshold": null,
      "damage": ""
    },
    "damage": {
      "parts": [
        [
          "1d6 + @mod +3",
          "slashing"
        ]
      ],
      "versatile": ""
    },
    "formula": "",
    "save": {
      "ability": "",
      "dc": null,
      "scaling": "spell"
    },
    "armor": {
      "value": 10
    },
    "hp": {
      "value": 0,
      "max": 0,
      "dt": null,
      "conditions": ""
    },
    "weaponType": "simpleM",
    "baseItem": "handaxe",
    "properties": {
      "lgt": true,
      "thr": true,
      "amm": false,
      "hvy": false,
      "fin": false,
      "fir": false,
      "foc": false,
      "lod": false,
      "rch": false,
      "rel": false,
      "ret": false,
      "spc": false,
      "two": false,
      "ver": false,
      "mgc": true
    },
    "proficient": false,
    "attributes": {
      "spelldc": 10
    }
  },
  "_key": "!items!A41W3rfC7zyb6WJp"
}