{
  "name": "Stone of Controlling Earth Elementals",
  "type": "consumable",
  "img": "icons/commodities/treasure/token-runed-os-grey.webp",
  "effects": [],
  "folder": null,
  "sort": 0,
  "flags": {
    "core": {
      "sourceId": "Compendium.dnd5e.items.TWFS1BtruQeE10BY"
    }
  },
  "_id": "jtukZ92yNw1bDFNf",
  "_stats": {
    "coreVersion": "12.331",
    "systemId": null,
    "systemVersion": null,
    "createdTime": null,
    "modifiedTime": null,
    "lastModifiedBy": null,
    "compendiumSource": null,
    "duplicateSource": null
  },
  "ownership": {
    "default": 0,
    "4lCdaYwhvK1T68Lv": 3
  },
  "system": {
    "description": {
      "value": "<p><em>Objet merveilleux</em></p>\n<p>Si la pierre est en contact avec le sol, vous pouvez utiliser une action pour prononcer le mot de commande de la pierre et invoquer un @Compendium[dnd5e.monsters.sApYLZj9PTZ40wJr]{Earth Elemental}, comme si vous aviez lancé le sort @Compendium[dnd5e.spells.1LkZvINag7KqBmDR]{Conjure Elemental}. La pierre ne peut plus être utilisée de cette manière avant le prochain lever du soleil.</p>\n<p>La pierre pèse 5 livres.</p>",
      "chat": "",
      "unidentified": ""
    },
    "source": "DMG pg. 205",
    "quantity": 1,
    "weight": 5,
    "price": 8000,
    "attunement": 0,
    "equipped": false,
    "rarity": "rare",
    "identified": true,
    "activation": {
      "type": "action",
      "cost": 1,
      "condition": "Command word."
    },
    "duration": {
      "value": 1,
      "units": "hour"
    },
    "target": {
      "value": 10,
      "width": null,
      "units": "ft",
      "type": "square"
    },
    "range": {
      "value": 90,
      "long": 0,
      "units": "ft"
    },
    "uses": {
      "value": 1,
      "max": 1,
      "per": "day",
      "autoDestroy": false,
      "autoUse": true
    },
    "consume": {
      "type": "",
      "target": null,
      "amount": null
    },
    "ability": null,
    "actionType": "",
    "attackBonus": 0,
    "chatFlavor": "",
    "critical": {
      "threshold": null,
      "damage": ""
    },
    "damage": {
      "parts": [],
      "versatile": ""
    },
    "formula": "",
    "save": {
      "ability": "",
      "dc": null,
      "scaling": "spell"
    },
    "consumableType": "trinket",
    "attributes": {
      "spelldc": 10
    }
  },
  "_key": "!items!jtukZ92yNw1bDFNf"
}