{
  "name": "Tarokka Deck",
  "type": "equipment",
  "img": "icons/sundries/gaming/playing-cards-brown.webp",
  "effects": [],
  "folder": null,
  "sort": 0,
  "flags": {
    "mre-dnd5e": {
      "formulaGroups": [
        {
          "label": "Primary",
          "formulaSet": []
        }
      ]
    },
    "magicitems": {
      "enabled": false,
      "equipped": false,
      "attuned": false,
      "charges": "0",
      "chargeType": "c1",
      "destroy": false,
      "destroyFlavorText": "reaches 0 charges: it crumbles into ashes and is destroyed.",
      "rechargeable": false,
      "recharge": "0",
      "rechargeType": "t1",
      "rechargeUnit": "r1",
      "sorting": "l"
    },
    "core": {
      "sourceId": "Item.9hYp3dzQxYksLKJm"
    }
  },
  "_id": "26FPKuZqYXbsqdVG",
  "_stats": {
    "coreVersion": "12.331",
    "systemId": null,
    "systemVersion": null,
    "createdTime": null,
    "modifiedTime": null,
    "lastModifiedBy": null,
    "compendiumSource": null,
    "duplicateSource": null
  },
  "ownership": {
    "default": 0,
    "UjfixXuqstXNdypa": 3
  },
  "system": {
    "description": {
      "value": "<p>Les Vistani ont depuis longtemps été maîtres de la divination. Entre les mains d'un voyant Vistani, un jeu de cartes tarokka peut raconter des histoires du futur et fournir des réponses à de nombreuses questions sombres et mystérieuses.</p>\n<p>Bien que la qualité artisanale et artistique des cartes puisse varier d'un jeu à l'autre, la capacité des cartes à appeler des informations sur le futur est bien plus précieuse que la valeur monétaire d'un jeu.</p>\n<p>N'importe qui peut fabriquer un jeu de cartes tarokka, mais seul quelqu'un de sang Vistani peut imprégner les cartes du don de prophétie. Une fois qu'elles sont fabriquées et activées, elles doivent être stockées conformément à la tradition ancienne, sinon elles perdent leur efficacité. Lorsque les cartes tarokka ne sont pas utilisées, elles doivent être enveloppées dans de la soie et stockées dans une boîte en bois.</p>\n<p> </p>\n<p>Un jeu tarokka comporte <a href=\"https://5e.tools/adventure.html#cos,22\" target=\"_blank\" rel=\"noopener\">cinquante-quatre cartes</a>, chacune ayant son propre nom. Quarante d'entre elles composent le jeu commun, qui est divisé en quatre ensembles : épées, pièces, étoiles et glyphes.</p>\n<p>Chaque ensemble contient des cartes numérotées de un à neuf, plus une dixième carte appelée le maître de cet ensemble. Une carte peut être désignée par son ensemble ou par son nom. Par exemple, le trois de glyphes est également connu sous le nom de guérisseur, et la carte du magicien est également connue sous le nom de maître des étoiles.</p>\n<p>Les quatorze cartes restantes constituent le jeu supérieur, qui symbolise les forces naturelles du multivers. Ces cartes sont représentées par un symbole de couronne et sont les cartes les plus puissantes du jeu.</p>",
      "chat": "",
      "unidentified": ""
    },
    "source": "VRGR",
    "quantity": 1,
    "weight": 0,
    "price": "0",
    "attunement": 0,
    "equipped": false,
    "rarity": "uncommon",
    "identified": true,
    "activation": {
      "type": "",
      "cost": 0,
      "condition": ""
    },
    "duration": {
      "value": null,
      "units": ""
    },
    "target": {
      "value": null,
      "width": null,
      "units": "",
      "type": ""
    },
    "range": {
      "value": null,
      "long": null,
      "units": ""
    },
    "uses": {
      "value": null,
      "max": "",
      "per": null
    },
    "consume": {
      "type": "",
      "target": null,
      "amount": null
    },
    "ability": null,
    "actionType": "",
    "attackBonus": 0,
    "chatFlavor": "",
    "critical": {
      "threshold": null,
      "damage": ""
    },
    "damage": {
      "parts": [],
      "versatile": ""
    },
    "formula": "",
    "save": {
      "ability": "",
      "dc": null,
      "scaling": "spell"
    },
    "armor": {
      "value": null,
      "type": "trinket",
      "dex": null
    },
    "hp": {
      "value": 0,
      "max": 0,
      "dt": null,
      "conditions": ""
    },
    "baseItem": "",
    "speed": {
      "value": null,
      "conditions": ""
    },
    "strength": 0,
    "stealth": false,
    "proficient": true
  },
  "_key": "!items!26FPKuZqYXbsqdVG"
}