{
  "_id": "pDaEKKc4p87xp30S",
  "name": "Winged Boots",
  "type": "equipment",
  "img": "icons/equipment/feet/boots-collared-simple-leather.webp",
  "effects": [
    {
      "_id": "YFSlU3S3B6DGH6Gt",
      "changes": [
        {
          "key": "system.attributes.movement.fly",
          "mode": 2,
          "value": "@attributes.speed.value",
          "priority": 20
        }
      ],
      "disabled": false,
      "duration": {
        "startTime": null,
        "seconds": null,
        "combat": null,
        "rounds": null,
        "turns": null,
        "startRound": null,
        "startTurn": null
      },
      "origin": "Compendium.5e-complete-fr.5e-items.pDaEKKc4p87xp30S",
      "transfer": true,
      "flags": {
        "dae": {
          "stackable": "none",
          "specialDuration": [],
          "transfer": true
        }
      },
      "tint": "#ffffff",
      "_stats": {
        "coreVersion": "12.331",
        "systemId": null,
        "systemVersion": null,
        "createdTime": null,
        "modifiedTime": null,
        "lastModifiedBy": null,
        "compendiumSource": null,
        "duplicateSource": null
      },
      "name": "Winged Boots: Flight",
      "img": "icons/svg/aura.svg",
      "type": "base",
      "system": {},
      "description": "",
      "statuses": [],
      "sort": 0,
      "_key": "!items.effects!pDaEKKc4p87xp30S.YFSlU3S3B6DGH6Gt"
    }
  ],
  "folder": null,
  "sort": 0,
  "flags": {
    "core": {
      "sourceId": "Compendium.dnd5e.items.YjImJ3cVnArHH4ES"
    }
  },
  "_stats": {
    "coreVersion": "12.331",
    "systemId": null,
    "systemVersion": null,
    "createdTime": null,
    "modifiedTime": null,
    "lastModifiedBy": null,
    "compendiumSource": null,
    "duplicateSource": null
  },
  "ownership": {
    "default": 0,
    "4lCdaYwhvK1T68Lv": 3
  },
  "system": {
    "description": {
      "value": "<p><em>Objet merveilleux, (nécessite l'accord)</em></p>\n<p>Tant que vous portez ces bottes, vous avez une vitesse de vol égale à votre vitesse de marche. Vous pouvez utiliser les bottes pour voler pendant jusqu'à 4 heures, d'un seul coup ou en plusieurs vols plus courts, chacun utilisant un minimum de 1 minute de la durée. Si vous êtes en vol lorsque la durée expire, vous descendez à une vitesse de 9 mètres par round jusqu'à ce que vous atterrissiez.</p>\n<p>Les bottes récupèrent 2 heures de capacité de vol pour chaque 12 heures où elles ne sont pas utilisées.</p>",
      "chat": "",
      "unidentified": ""
    },
    "source": "DMG pg. 214",
    "quantity": 1,
    "weight": 1,
    "price": 8000,
    "attunement": 1,
    "equipped": false,
    "rarity": "uncommon",
    "identified": true,
    "activation": {
      "type": "none",
      "cost": 0,
      "condition": ""
    },
    "duration": {
      "value": 4,
      "units": "hour"
    },
    "target": {
      "value": null,
      "width": null,
      "units": null,
      "type": "self"
    },
    "range": {
      "value": null,
      "long": null,
      "units": "self"
    },
    "uses": {
      "value": null,
      "max": null,
      "per": ""
    },
    "consume": {
      "type": "",
      "target": null,
      "amount": null
    },
    "ability": null,
    "actionType": "",
    "attackBonus": 0,
    "chatFlavor": "",
    "critical": {
      "threshold": null,
      "damage": ""
    },
    "damage": {
      "parts": [],
      "versatile": ""
    },
    "formula": "",
    "save": {
      "ability": "",
      "dc": null,
      "scaling": "spell"
    },
    "armor": {
      "value": null,
      "type": "clothing",
      "dex": null
    },
    "hp": {
      "value": 0,
      "max": 0,
      "dt": null,
      "conditions": ""
    },
    "baseItem": "",
    "speed": {
      "value": null,
      "conditions": ""
    },
    "strength": 0,
    "stealth": false,
    "proficient": false,
    "attributes": {
      "spelldc": 10
    }
  },
  "_key": "!items!pDaEKKc4p87xp30S"
}