{
  "_id": "WStcQdlUxqmTFMtu",
  "name": "Dark Delirium",
  "type": "feat",
  "img": "icons/magic/control/control-influence-rally-purple.webp",
  "effects": [],
  "folder": null,
  "sort": 0,
  "flags": {
    "mre-dnd5e": {
      "formulaGroups": [
        {
          "label": "Primary",
          "formulaSet": []
        }
      ]
    },
    "magicitems": {
      "enabled": false,
      "equipped": false,
      "attuned": false,
      "charges": "0",
      "chargeType": "c1",
      "destroy": false,
      "destroyFlavorText": "reaches 0 charges: it crumbles into ashes and is destroyed.",
      "rechargeable": false,
      "recharge": "0",
      "rechargeType": "t1",
      "rechargeUnit": "r1",
      "sorting": "l"
    },
    "core": {
      "sourceId": "Item.KYLnHF4wqyqyl8XJ"
    }
  },
  "_stats": {
    "coreVersion": "12.331",
    "systemId": null,
    "systemVersion": null,
    "createdTime": null,
    "modifiedTime": null,
    "lastModifiedBy": null,
    "compendiumSource": null,
    "duplicateSource": null
  },
  "ownership": {
    "default": 0,
    "UjfixXuqstXNdypa": 3
  },
  "system": {
    "description": {
      "value": "<p>À partir du 14e niveau, vous pouvez plonger une créature dans un royaume illusoire. En tant qu'action, choisissez une créature que vous pouvez voir à moins de 18 mètres de vous. Elle doit effectuer un jet de sauvegarde de Sagesse contre votre DC de sauvegarde de sort de warlock. En cas d'échec, elle est <strong>charmed</strong> ou <strong>frightened</strong> par vous (à votre choix) pendant 1 minute ou jusqu'à ce que votre concentration soit rompue (comme si vous concentriez un sort). Cet effet prend fin prématurément si la créature subit des dégâts.</p>\n<p>Jusqu'à la fin de cette illusion, la créature pense être perdue dans un royaume brumeux, dont l'apparence est de votre choix. La créature ne peut voir et entendre que lui-même, vous et l'illusion.</p>\n<p>Vous devez terminer un <strong>short</strong> ou <strong>long rest</strong> avant de pouvoir utiliser cette fonctionnalité à nouveau.</p>",
      "chat": "",
      "unidentified": ""
    },
    "source": "PHB",
    "activation": {
      "type": "action",
      "cost": 1,
      "condition": ""
    },
    "duration": {
      "value": 1,
      "units": "minute"
    },
    "target": {
      "value": 1,
      "width": null,
      "units": "",
      "type": "creature"
    },
    "range": {
      "value": 60,
      "long": null,
      "units": "ft"
    },
    "uses": {
      "value": 1,
      "max": "1",
      "per": "sr"
    },
    "consume": {
      "type": "",
      "target": "",
      "amount": null
    },
    "ability": "",
    "actionType": "save",
    "attackBonus": 0,
    "chatFlavor": "",
    "critical": {
      "threshold": null,
      "damage": ""
    },
    "damage": {
      "parts": [],
      "versatile": ""
    },
    "formula": "",
    "save": {
      "ability": "wis",
      "dc": null,
      "scaling": "spell"
    },
    "requirements": "The Archfey 14",
    "recharge": {
      "value": null,
      "charged": false
    }
  },
  "_key": "!items!WStcQdlUxqmTFMtu"
}