{
  "_id": "PfXZJ5PxBIFaIHWd",
  "name": "Reaper",
  "type": "feat",
  "img": "icons/magic/death/skull-pile-glowing-pink.webp",
  "effects": [],
  "folder": null,
  "sort": 0,
  "flags": {
    "betterRolls5e": {
      "quickDesc": {
        "value": true,
        "altValue": true
      },
      "quickProperties": {
        "value": true,
        "altValue": true
      },
      "quickOther": {
        "value": true,
        "altValue": true
      },
      "quickFlavor": {
        "value": true,
        "altValue": true
      }
    },
    "core": {
      "sourceId": "Item.XumaIsamjQg4GZrA"
    }
  },
  "_stats": {
    "coreVersion": "12.331",
    "systemId": null,
    "systemVersion": null,
    "createdTime": null,
    "modifiedTime": null,
    "lastModifiedBy": null,
    "compendiumSource": null,
    "duplicateSource": null
  },
  "ownership": {
    "default": 0,
    "LCw1mxC8S2Al3dWA": 3
  },
  "system": {
    "description": {
      "value": "<p>À 1er niveau, vous apprenez un <strong>necromancy</strong> cantrip de votre choix parmi n'importe quelle liste de sorts. Lorsque vous lancez un necromancy cantrip qui cible normalement une seule créature, le sort peut cibler à la place deux créatures à portée et à moins de 5 pieds l'une de l'autre.</p>",
      "chat": "",
      "unidentified": ""
    },
    "source": "",
    "activation": {
      "type": "",
      "cost": 0,
      "condition": ""
    },
    "duration": {
      "value": null,
      "units": ""
    },
    "target": {
      "value": null,
      "width": null,
      "units": "",
      "type": ""
    },
    "range": {
      "value": null,
      "long": null,
      "units": ""
    },
    "uses": {
      "value": null,
      "max": "",
      "per": null
    },
    "consume": {
      "type": "",
      "target": null,
      "amount": null
    },
    "ability": null,
    "actionType": "",
    "attackBonus": 0,
    "chatFlavor": "",
    "critical": {
      "threshold": null,
      "damage": ""
    },
    "damage": {
      "parts": [],
      "versatile": ""
    },
    "formula": "",
    "save": {
      "ability": "",
      "dc": null,
      "scaling": "spell"
    },
    "requirements": "Death Domain 1",
    "recharge": {
      "value": null,
      "charged": false
    }
  },
  "_key": "!items!PfXZJ5PxBIFaIHWd"
}
