{
  "_id": "stYxidl8XEOAVq8X",
  "name": "Shadow Martyr",
  "type": "feat",
  "img": "icons/magic/unholy/beam-impact-purple.webp",
  "effects": [],
  "folder": null,
  "sort": 0,
  "flags": {
    "betterRolls5e": {
      "quickDesc": {
        "value": true,
        "altValue": true
      },
      "quickProperties": {
        "value": true,
        "altValue": true
      },
      "quickOther": {
        "value": true,
        "altValue": true
      },
      "quickFlavor": {
        "value": true,
        "altValue": true
      },
      "quickCharges": {
        "value": {
          "use": true
        },
        "altValue": {
          "use": true
        }
      }
    },
    "core": {
      "sourceId": "Item.VYHrKwOUMTNsW8BE"
    },
    "magicitems": {
      "enabled": false,
      "equipped": false,
      "attuned": false,
      "charges": "0",
      "chargeType": "c1",
      "destroy": false,
      "destroyFlavorText": "reaches 0 charges: it crumbles into ashes and is destroyed.",
      "rechargeable": false,
      "recharge": "0",
      "rechargeType": "t1",
      "rechargeUnit": "r1",
      "sorting": "l"
    }
  },
  "_stats": {
    "coreVersion": "12.331",
    "systemId": null,
    "systemVersion": null,
    "createdTime": null,
    "modifiedTime": null,
    "lastModifiedBy": null,
    "compendiumSource": null,
    "duplicateSource": null
  },
  "ownership": {
    "default": 0,
    "LCw1mxC8S2Al3dWA": 3
  },
  "system": {
    "description": {
      "value": "<p>À partir du 10ème niveau, vous pouvez faire en sorte que votre écho se jette devant une attaque dirigée contre une autre créature que vous pouvez voir. Avant que le jet d'attaque ne soit effectué, vous pouvez utiliser votre réaction pour téléporter l'écho vers un espace inoccupé à moins de 2 mètres de la créature ciblée. Le jet d'attaque qui a déclenché la réaction est effectué contre votre écho.</p>\n<p>Une fois que vous utilisez cette fonctionnalité, vous ne pouvez pas l'utiliser à nouveau jusqu'à ce que vous terminiez un repos court ou long.</p>",
      "chat": "",
      "unidentified": ""
    },
    "source": "XGW",
    "activation": {
      "type": "reaction",
      "cost": 1,
      "condition": ""
    },
    "duration": {
      "value": null,
      "units": ""
    },
    "target": {
      "value": null,
      "width": null,
      "units": "",
      "type": ""
    },
    "range": {
      "value": 5,
      "long": null,
      "units": "ft"
    },
    "uses": {
      "value": 1,
      "max": "1",
      "per": "sr"
    },
    "consume": {
      "type": "",
      "target": "",
      "amount": null
    },
    "ability": null,
    "actionType": "",
    "attackBonus": 0,
    "chatFlavor": "",
    "critical": {
      "threshold": null,
      "damage": ""
    },
    "damage": {
      "parts": [],
      "versatile": ""
    },
    "formula": "",
    "save": {
      "ability": "",
      "dc": null,
      "scaling": "spell"
    },
    "requirements": "Chevalier Echo 10",
    "recharge": {
      "value": null,
      "charged": false
    }
  },
  "_key": "!items!stYxidl8XEOAVq8X"
}